{
  "$schema": "https://melvoridle.com/assets/schema/gameData.json",
  "namespace": "rielkConstruction",
  "data": {
    "attacks": [],
    "combatEffects": [],
    "items": [
      {
        "modifiers": {
          "flatSlayerAreaEffectNegation": 5,
          "doubleSlayerTaskKillChance": 5
        },
        "enemyModifiers": {
          "flatRangedMaxHit": 5
        },
        "conditionalModifiers": [
          {
            "condition": {
              "conditions": [
                {
                  "type": "WeaponType",
                  "weaponType": "WTM:HeavyBows"
                },
                {
                  "type": "FightingSlayerTask"
                }
              ]
            },
            "modifiers": {
              "rangedCritChance": 2.5,
              "critMultiplier": 100
            }
          }
        ],
        "combatEffects": [
          {
            "condition": {
              "type": "WeaponType",
              "weaponType": "WTM:HeavyBows"
            },
            "appliesWhen": "HitWithAttack",
            "chance": 5,
            "effectID": "WTM:Arrowstruck"
          }
        ],
      }
    ]
  }
}